{
  "main": {
    "id": "942b662b40fb0550",
    "type": "split",
    "children": [
      {
        "id": "e90f64dd459856d1",
        "type": "tabs",
        "children": [
          {
            "id": "2c6cc5955d5c0382",
            "type": "leaf",
            "state": {
              "type": "markdown",
              "state": {
                "file": "README.md",
                "mode": "source",
                "source": false
              },
              "icon": "lucide-file",
              "title": "README"
            }
          },
          {
            "id": "9d893485afed3b2d",
            "type": "leaf",
            "state": {
              "type": "markdown",
              "state": {
                "file": "API Penetration Testing/Lab Setup.md",
                "mode": "source",
                "source": false
              },
              "icon": "lucide-file",
              "title": "Lab Setup"
            }
          },
          {
            "id": "0c4bd83f75650e0d",
            "type": "leaf",
            "state": {
              "type": "markdown",
              "state": {
                "file": "API Penetration Testing/API Recoinassance/Passive Recoinassance.md",
                "mode": "source",
                "source": false
              },
              "icon": "lucide-file",
              "title": "Passive Recoinassance"
            }
          },
          {
            "id": "cbd14dcfd190d7aa",
            "type": "leaf",
            "state": {
              "type": "markdown",
              "state": {
                "file": "API Penetration Testing/API Recoinassance/Passive Recoinassance.md",
                "mode": "source",
                "source": false
              },
              "icon": "lucide-file",
              "title": "Passive Recoinassance"
            }
          },
          {
            "id": "9d5214d36ca2f591",
            "type": "leaf",
            "state": {
              "type": "markdown",
              "state": {
                "file": "API Penetration Testing/Lab Setup.md",
                "mode": "source",
                "source": false
              },
              "icon": "lucide-file",
              "title": "Lab Setup"
            }
          }
        ],
        "currentTab": 4
      }
    ],
    "direction": "vertical"
  },
  "left": {
    "id": "f3881ad7e6155fc9",
    "type": "split",
    "children": [
      {
        "id": "659efffae8d73e92",
        "type": "tabs",
        "children": [
          {
            "id": "32d3c304bae0a383",
            "type": "leaf",
            "state": {
              "type": "file-explorer",
              "state": {
                "sortOrder": "alphabetical",
                "autoReveal": false
              },
              "icon": "lucide-folder-closed",
              "title": "Files"
            }
          },
          {
            "id": "512f08d30b29b412",
            "type": "leaf",
            "state": {
              "type": "search",
              "state": {
                "query": "",
                "matchingCase": false,
                "explainSearch": false,
                "collapseAll": false,
                "extraContext": false,
                "sortOrder": "alphabetical"
              },
              "icon": "lucide-search",
              "title": "Search"
            }
          },
          {
            "id": "14ba64f41db584e4",
            "type": "leaf",
            "state": {
              "type": "bookmarks",
              "state": {},
              "icon": "lucide-bookmark",
              "title": "Bookmarks"
            }
          }
        ]
      }
    ],
    "direction": "horizontal",
    "width": 300
  },
  "right": {
    "id": "8d189f9aafec1599",
    "type": "split",
    "children": [
      {
        "id": "96bb9e47dec7ddf5",
        "type": "tabs",
        "children": [
          {
            "id": "b845acd28a7480ec",
            "type": "leaf",
            "state": {
              "type": "backlink",
              "state": {
                "file": "API Penetration Testing/Lab Setup.md",
                "collapseAll": false,
                "extraContext": false,
                "sortOrder": "alphabetical",
                "showSearch": false,
                "searchQuery": "",
                "backlinkCollapsed": false,
                "unlinkedCollapsed": true
              },
              "icon": "links-coming-in",
              "title": "Backlinks for Lab Setup"
            }
          },
          {
            "id": "b3a36a8b2bd527a4",
            "type": "leaf",
            "state": {
              "type": "outgoing-link",
              "state": {
                "file": "API Penetration Testing/Lab Setup.md",
                "linksCollapsed": false,
                "unlinkedCollapsed": true
              },
              "icon": "links-going-out",
              "title": "Outgoing links from Lab Setup"
            }
          },
          {
            "id": "2ce54781b74b6571",
            "type": "leaf",
            "state": {
              "type": "tag",
              "state": {
                "sortOrder": "frequency",
                "useHierarchy": true,
                "showSearch": false,
                "searchQuery": ""
              },
              "icon": "lucide-tags",
              "title": "Tags"
            }
          },
          {
            "id": "84aeb0677de68367",
            "type": "leaf",
            "state": {
              "type": "outline",
              "state": {
                "file": "API Penetration Testing/Lab Setup.md",
                "followCursor": false,
                "showSearch": false,
                "searchQuery": ""
              },
              "icon": "lucide-list",
              "title": "Outline of Lab Setup"
            }
          }
        ]
      }
    ],
    "direction": "horizontal",
    "width": 300,
    "collapsed": true
  },
  "left-ribbon": {
    "hiddenItems": {
      "switcher:Open quick switcher": false,
      "graph:Open graph view": false,
      "canvas:Create new canvas": false,
      "daily-notes:Open today's daily note": false,
      "templates:Insert template": false,
      "command-palette:Open command palette": false
    }
  },
  "active": "9d5214d36ca2f591",
  "lastOpenFiles": [
    "API Penetration Testing/API Recoinassance/Active Reconnaissance.md",
    "API Penetration Testing/Endpoint Analysis/Untitled",
    "API Penetration Testing/Endpoint Analysis",
    "API Penetration Testing/API Recoinassance/Passive Recoinassance.md",
    "API Penetration Testing/Lab Setup.md",
    "API Penetration Testing/References.md",
    "API Penetration Testing",
    "API Penetration Testing/API Recoinassance",
    "README.md"
  ]
}